testing_absolute_imports/.idea/.gitignore
testing_absolute_imports/.idea/inspectionProfiles/Project_Default.xml
testing_absolute_imports/.idea/inspectionProfiles/profiles_settings.xml
testing_absolute_imports/.idea/misc.xml
testing_absolute_imports/.idea/modules.xml
testing_absolute_imports/.idea/testing_absolute_imports.iml
testing_absolute_imports/.idea/workspace.xml
testing_absolute_imports/Test/first_test.py
testing_absolute_imports/__init__.py
testing_absolute_imports/main.py
testing_absolute_imports/printing.py
testing_absolute_imports/secondprint.py
testing_absolute_imports-0.5.dist-info/WHEEL
testing_absolute_imports-0.5.dist-info/METADATA
testing_absolute_imports-0.5.dist-info/RECORD
