Metadata-Version: 2.1
Name: testing-absolute-imports
Version: 0.5
Summary: Personal project to test absolute importing inside a distribution package
Author: Yashesh Dasari
Requires-Python: >=3.8,<4.0
Classifier: Programming Language :: Python :: 3
Classifier: Programming Language :: Python :: 3.10
Classifier: Programming Language :: Python :: 3.8
Classifier: Programming Language :: Python :: 3.9
